wpbackup2/__init__.py
wpbackup2/__main__.py
wpbackup2/__version__.py
wpbackup2/classes/__init__.py
wpbackup2/classes/wp_internal_backup.py
wpbackup2/classes/wp_internal_restore.py
wpbackup2/classes/wpbackup.py
wpbackup2/classes/wpsite.py
wpbackup2/exceptions/__init__.py
wpbackup2/exceptions/backup_not_found.py
wpbackup2/exceptions/config_not_found.py
wpbackup2/exceptions/database_backup_failed.py
wpbackup2/exceptions/database_mysql_failed.py
wpbackup2/exceptions/database_restore_failed.py
wpbackup2-0.2.21.dist-info/LICENSE
wpbackup2-0.2.21.dist-info/METADATA
wpbackup2-0.2.21.dist-info/WHEEL
wpbackup2-0.2.21.dist-info/top_level.txt
wpbackup2-0.2.21.dist-info/RECORD
