Metadata-Version: 2.1
Name: wpbackup2
Version: 0.2.21
Summary: Backup and restore all your self-hosted WordPress content
Home-page: https://github.com/ravensorb/py-wordpress-backup
Author: Shawn Anderson
Author-email: code@eye-catcher.com
License: MIT License
Platform: UNKNOWN
Classifier: Development Status :: 4 - Beta
Classifier: Environment :: Console
Classifier: Intended Audience :: Developers
Classifier: License :: OSI Approved :: MIT License
Classifier: Natural Language :: English
Classifier: Programming Language :: Python :: 3
Classifier: Operating System :: OS Independent
Classifier: Topic :: Internet :: WWW/HTTP :: Site Management
Requires-Dist: chesney (<=2.0,>=1.0)
Requires-Dist: wpconfigr (<=2.0.0,>=1.0.0)
Requires-Dist: wpdatabase2 (>=0.0.13)
Provides-Extra: dev
Requires-Dist: autopep8 ; extra == 'dev'
Requires-Dist: coverage ; extra == 'dev'
Requires-Dist: pylint ; extra == 'dev'
